nullWriter/__init__.py
nullWriter/nullWriter.py
nullWriter-0.1.3.dist-info/METADATA
nullWriter-0.1.3.dist-info/WHEEL
nullWriter-0.1.3.dist-info/top_level.txt
nullWriter-0.1.3.dist-info/RECORD
