Metadata-Version: 2.1
Name: nullWriter
Version: 0.1.3
Summary: Hello
Home-page: https://github.com/bdoohan-goog/NullModeler
Author: Brendan Doohan
Author-email: bdoohan@google.com
License: MIT
Download-URL: https://pypi.org/project/nullWriter/
Keywords: nullWriter
Platform: UNKNOWN
Requires-Dist: sklearn
Requires-Dist: numpy
